civicutils/__init__.py
civicutils/filtering.py
civicutils/match.py
civicutils/query.py
civicutils/read_and_write.py
civicutils/utils.py
civicutils/data/data.yml
civicutils/data/example_cnv.txt
civicutils/data/example_expr.txt
civicutils/data/example_snv.txt
civicutils-1.0.3.dist-info/METADATA
civicutils-1.0.3.dist-info/WHEEL
civicutils-1.0.3.dist-info/licenses/LICENSE.md
civicutils-1.0.3.dist-info/RECORD
