Metadata-Version: 2.1
Name: civicutils
Version: 1.0.3
Summary: Python package for querying, matching and downstream processing of CIViC information.
Project-URL: Homepage, https://github.com/ETH-NEXUS/civicutils
Project-URL: Bug Tracker, https://github.com/ETH-NEXUS/civicutils/issues
Author-email: María Lourdes Rosano-Gonzalez <lourdes.rosanogonzalez@gmail.com>, "Vipin T. Sreedharan" <vipin.sreedharan@nexus.ethz.ch>, Antoine Hanns <hanns@nexus.ethz.ch>, "Daniel J. Stekhoven" <stekhoven@nexus.ethz.ch>, Franziska Singer <singer@nexus.ethz.ch>
Maintainer-email: Antoine Hanns <hanns@nexus.ethz.ch>
License:                     GNU GENERAL PUBLIC LICENSE
License-File: LICENSE.md
Keywords: API query,CIViC database,clinical relevance,in-silico drug prediction,variant prioritization
Classifier: License :: OSI Approved :: GNU General Public License v3 (GPLv3)
Classifier: Operating System :: MacOS
Classifier: Programming Language :: Python :: 3
Requires-Python: >=3.7
Requires-Dist: civicpy>=3.0.0
